ontologymodel/__init__.py
ontologymodel-0.1.0.dist-info/METADATA
ontologymodel-0.1.0.dist-info/WHEEL
ontologymodel-0.1.0.dist-info/top_level.txt
ontologymodel-0.1.0.dist-info/RECORD
