Metadata-Version: 2.1
Name: ontologymodel
Version: 0.1.0
Summary: OntologyModel Library
Author-email: Kevin <kevinqz@gmail.com>
Requires-Python: >=3.11
